{"id":3132,"openDoarId":null,"name":"Revista Letras \u0026 Letras","email":"","oaiPmhUrl":"http:\/\/www.letraseletras.ileel.ufu.br\/oai","homepageUrl":"http:\/\/www.letraseletras.ileel.ufu.br","software":null,"metadataFormat":"oai_dc","createdDate":"2017-08-31T15:54:37+01:00","location":{"countryCode":"br","latitude":0,"longitude":0},"logo":"https:\/\/api.core.ac.uk\/data-providers\/3132\/logo","type":"REPOSITORY","rorId":"https:\/\/ror.org\/04x3wvr31","institutionName":"Federal University of Uberl\u00e2ndia","aliases":["pt: Universidade Federal de Uberl\u00e2ndia","UFU"],"otherIdentifiers":{"GRID":{"preferred":"grid.411284.a","all":"grid.411284.a"},"ISNI":{"all":"0000 0004 4647 6936"},"FundRef":{"all":"501100003105"},"Wikidata":{"all":"Q5440489"}}}