{"id":2609,"openDoarId":null,"name":"Washington Research Library Consortium - Digital Collections","email":"","oaiPmhUrl":"http:\/\/islandora.wrlc.org\/oai2","homepageUrl":"http:\/\/islandora.wrlc.org","software":null,"metadataFormat":"oai_dc","createdDate":"2017-04-10T00:05:48+01:00","location":{"countryCode":"us","latitude":0,"longitude":0},"logo":"https:\/\/api.core.ac.uk\/data-providers\/2609\/logo","type":"REPOSITORY","rorId":null,"institutionName":null,"aliases":[],"otherIdentifiers":null}