{"id":736,"openDoarId":411,"name":"Caltech Archives Oral Histories Online","email":"","oaiPmhUrl":"http:\/\/oralhistories.library.caltech.edu\/cgi\/oai2","homepageUrl":"http:\/\/oralhistories.library.caltech.edu","software":null,"metadataFormat":"oai_dc","createdDate":"2016-05-06T18:25:04+01:00","location":{"countryCode":"US","latitude":34.1377,"longitude":-118.1253},"logo":"https:\/\/api.core.ac.uk\/data-providers\/736\/logo","type":"REPOSITORY","rorId":"https:\/\/ror.org\/01e6j9276","institutionName":"Caltech Submillimeter Observatory","aliases":["CSO"],"otherIdentifiers":{"GRID":{"preferred":"grid.440394.e","all":"grid.440394.e"},"Wikidata":{"all":"Q1027482"}}}