{"id":8221,"openDoarId":null,"name":"koara-a","email":"","oaiPmhUrl":"http:\/\/koara-a.lib.keio.ac.jp\/xoonips\/modules\/xoonips\/oai.php","homepageUrl":"http:\/\/koara-a.lib.keio.ac.jp","software":null,"metadataFormat":"oai_dc","createdDate":"2019-06-26T08:26:01+01:00","location":{"countryCode":"","latitude":0,"longitude":0},"logo":"https:\/\/api.core.ac.uk\/data-providers\/8221\/logo","type":"REPOSITORY","rorId":"https:\/\/ror.org\/02kn6nx58","institutionName":"Keio University","aliases":["Kei\u014d Gijuku Daigaku","ja: \u6176\u61c9\u7fa9\u587e\u5927\u5b66"],"otherIdentifiers":{"GRID":{"preferred":"grid.26091.3c","all":"grid.26091.3c"},"ISNI":{"all":"0000 0004 1936 9959"},"FundRef":{"all":"501100007467;501100001697"},"Wikidata":{"all":"Q815432"}}}