{"id":14,"openDoarId":900,"name":"Brunel University Research Archive","email":"bura@brunel.ac.uk","oaiPmhUrl":"https:\/\/bura.brunel.ac.uk\/oai\/request","homepageUrl":"https:\/\/bura.brunel.ac.uk","software":"dspace","metadataFormat":"oai_dc","createdDate":"2011-05-11T14:18:01+01:00","location":{"countryCode":"GB","latitude":51.5324044,"longitude":-0.4729931},"logo":"https:\/\/api.core.ac.uk\/data-providers\/14\/logo","type":"REPOSITORY","rorId":"https:\/\/ror.org\/00dn4t376","institutionName":"Brunel University London","aliases":["","",""],"otherIdentifiers":{"ISNI":{"preferred":null,"all":["0000 0001 0724 6933"]},"FundRef":{"preferred":null,"all":["100008475","501100007914"]},"HESA":{"preferred":null,"all":["0113"]},"UCAS":{"preferred":null,"all":["B84"]},"UKPRN":{"preferred":null,"all":["10000961"]},"OrgRef":{"preferred":null,"all":["155199"]},"Wikidata":{"preferred":null,"all":["Q932411"]},"GRID":{"preferred":"grid.7728.a","all":"grid.7728.a"}}}