{"id":3381,"openDoarId":null,"name":"Shenyang Institute of Automation,Chinese Academy Of Sciences","email":"","oaiPmhUrl":"http:\/\/ir.sia.ac.cn\/casirgrid-oai\/request","homepageUrl":"http:\/\/ir.sia.ac.cn","software":null,"metadataFormat":"oai_dc","createdDate":"2017-08-31T15:55:13+01:00","location":{"countryCode":"cn","latitude":41.8109,"longitude":123.495},"logo":"https:\/\/api.core.ac.uk\/data-providers\/3381\/logo","type":"REPOSITORY","rorId":null,"institutionName":null,"aliases":[],"otherIdentifiers":null}