{"id":387,"openDoarId":null,"name":"Memorial University Research Repository","email":"","oaiPmhUrl":"http:\/\/research.library.mun.ca\/cgi\/oai2","homepageUrl":"http:\/\/research.library.mun.ca","software":"eprints","metadataFormat":"oai_dc","createdDate":"2013-07-12T12:48:07+01:00","location":{"countryCode":"ca","latitude":47.5712,"longitude":-52.7347},"logo":"https:\/\/api.core.ac.uk\/data-providers\/387\/logo","type":"REPOSITORY","rorId":"https:\/\/ror.org\/04haebc03","institutionName":"Memorial University of Newfoundland","aliases":["Memorial University","MUN"],"otherIdentifiers":{"GRID":{"preferred":"grid.25055.37","all":"grid.25055.37"},"ISNI":{"all":"0000 0000 9130 6822"},"FundRef":{"preferred":501100005616,"all":"501100005616;501100000084"},"Wikidata":{"all":"Q1895354"}}}