{"id":3581,"openDoarId":null,"name":"Case Western Reserve University School of Law","email":"","oaiPmhUrl":"http:\/\/scholarlycommons.law.case.edu\/do\/oai\/","homepageUrl":"http:\/\/scholarlycommons.law.case.edu","software":"scholarlycommons","metadataFormat":"oai_dc","createdDate":"2017-08-31T15:55:39+01:00","location":{"countryCode":"us","latitude":41.5104,"longitude":-81.6087},"logo":"https:\/\/api.core.ac.uk\/data-providers\/3581\/logo","type":"REPOSITORY","rorId":"https:\/\/ror.org\/051fd9666","institutionName":"Case Western Reserve University","aliases":["Case"," Case Western Reserve","CWRU"],"otherIdentifiers":{"GRID":{"preferred":"grid.67105.35","all":"grid.67105.35"},"ISNI":{"all":"0000 0001 2164 3847"},"FundRef":{"preferred":100008136,"all":"100008136;100008564;100008533;100008565"},"Wikidata":{"all":"Q1047060"}}}