{"id":2937,"openDoarId":null,"name":"e-ms Eprints Open Archive in Social Medicine and related fields","email":"","oaiPmhUrl":"http:\/\/e-ms.cilea.it\/perl\/oai2","homepageUrl":"http:\/\/e-ms.cilea.it","software":null,"metadataFormat":"oai_dc","createdDate":"2017-08-31T15:53:59+01:00","location":{"countryCode":"it","latitude":45.45,"longitude":9.16667},"logo":"https:\/\/api.core.ac.uk\/data-providers\/2937\/logo","type":"REPOSITORY","rorId":null,"institutionName":null,"aliases":[],"otherIdentifiers":null}