{"id":1949,"openDoarId":1619,"name":"Reposit\u00f3rio Cient\u00edfico da Universidade de \u00c9vora","email":"","oaiPmhUrl":"http:\/\/dspace.uevora.pt\/rdpc-oaiextended\/request","homepageUrl":"http:\/\/dspace.uevora.pt","software":null,"metadataFormat":"oai_dc","createdDate":"2016-11-08T12:28:59+00:00","location":{"countryCode":"PT","latitude":38.573,"longitude":-7.9054},"logo":"https:\/\/api.core.ac.uk\/data-providers\/1949\/logo","type":"REPOSITORY","rorId":"https:\/\/ror.org\/02gyps716","institutionName":"University of \u00c9vora","aliases":["pt: Universidade de \u00c9vora"],"otherIdentifiers":{"GRID":{"preferred":"grid.8389.a","all":"grid.8389.a"},"ISNI":{"all":"0000 0000 9310 6111"},"Wikidata":{"all":"Q1557861"}}}