{"id":243,"openDoarId":null,"name":"Architektur-Informatik","email":"","oaiPmhUrl":"http:\/\/architektur-informatik.scix.net\/cgi-bin\/works\/OAI","homepageUrl":"http:\/\/architektur-informatik.scix.net","software":null,"metadataFormat":"oai_dc","createdDate":"2012-10-09T13:37:51+01:00","location":{"countryCode":"de","latitude":49.95,"longitude":11.5833},"logo":"https:\/\/api.core.ac.uk\/data-providers\/243\/logo","type":"REPOSITORY","rorId":null,"institutionName":null,"aliases":[],"otherIdentifiers":null}