{"id":3372,"openDoarId":null,"name":"BIBLIOTECA USFQ","email":"","oaiPmhUrl":"http:\/\/repositorio.usfq.edu.ec\/oai\/request","homepageUrl":"http:\/\/repositorio.usfq.edu.ec","software":null,"metadataFormat":"oai_dc","createdDate":"2017-08-31T15:55:11+01:00","location":{"countryCode":"ec","latitude":-0.196809,"longitude":-78.4354},"logo":"https:\/\/api.core.ac.uk\/data-providers\/3372\/logo","type":"REPOSITORY","rorId":"https:\/\/ror.org\/01r2c3v86","institutionName":"Universidad San Francisco de Quito","aliases":["Universidad San Francisco","USFQ"],"otherIdentifiers":{"GRID":{"preferred":"grid.412251.1","all":"grid.412251.1"},"ISNI":{"all":"0000 0000 9008 4711"},"FundRef":{"preferred":501100010654,"all":"501100010654"},"Wikidata":{"all":"Q2495713"}}}