{"id":339,"openDoarId":null,"name":"Borys Grinchenko Kyiv University Institutional repository","email":"","oaiPmhUrl":"http:\/\/elibrary.kubg.edu.ua\/cgi\/oai2","homepageUrl":"http:\/\/elibrary.kubg.edu.ua","software":"eprints","metadataFormat":"oai_dc","createdDate":"2013-07-09T09:45:04+01:00","location":{"countryCode":"ua","latitude":50.5135,"longitude":30.4917},"logo":"https:\/\/api.core.ac.uk\/data-providers\/339\/logo","type":"REPOSITORY","rorId":"https:\/\/ror.org\/01t5m8p03","institutionName":"Borys Grinchenko Kyiv University","aliases":["pl: Uniwersytet Kijowski imienia Borysa Hrinczenki"," ru: \u041a\u0438\u0435\u0432\u0441\u043a\u0438\u0439 \u0443\u043d\u0438\u0432\u0435\u0440\u0441\u0438\u0442\u0435\u0442 \u0438\u043c\u0435\u043d\u0438 \u0411\u043e\u0440\u0438\u0441\u0430 \u0413\u0440\u0438\u043d\u0447\u0435\u043d\u043a\u043e"," uk: \u041a\u0438\u0457\u0432\u0441\u044c\u043a\u0438\u0439 \u0443\u043d\u0456\u0432\u0435\u0440\u0441\u0438\u0442\u0435\u0442 \u0456\u043c\u0435\u043d\u0456 \u0411\u043e\u0440\u0438\u0441\u0430 \u0413\u0440\u0456\u043d\u0447\u0435\u043d\u043a\u0430"],"otherIdentifiers":{"GRID":{"preferred":"grid.448561.a","all":"grid.448561.a"},"ISNI":{"preferred":"0000 0004 0582 3102","all":"0000 0004 0582 3102"},"Wikidata":{"all":"Q12110286"}}}