{"id":1253,"openDoarId":839,"name":"Cybertesis Pontificia Universidad Cat\u00f3lica de Valpara\u00edso","email":"","oaiPmhUrl":"http:\/\/cybertesis.ucv.cl\/sdx\/sdx\/oai\/pucv\/documents","homepageUrl":"http:\/\/cybertesis.ucv.cl","software":null,"metadataFormat":"oai_dc","createdDate":"2016-11-08T12:28:52+00:00","location":{"countryCode":"CL","latitude":-33.04778,"longitude":-71.60111},"logo":"https:\/\/api.core.ac.uk\/data-providers\/1253\/logo","type":"REPOSITORY","rorId":"https:\/\/ror.org\/02cafbr77","institutionName":"Pontificial Catholic University of Valparaiso","aliases":["Universidad Cat\u00f3lica de Valpara\u00edso","es: Pontificia Universidad Cat\u00f3lica de Valpara\u00edso","PUCV"],"otherIdentifiers":{"GRID":{"preferred":"grid.8170.e","all":"grid.8170.e"},"ISNI":{"all":"0000 0001 1537 5962"},"FundRef":{"preferred":501100007776,"all":"501100007776"},"Wikidata":{"all":"Q1284408"}}}