{"id":7969,"openDoarId":null,"name":"JAMMO    ISSN 2146-3328","email":"","oaiPmhUrl":"http:\/\/www.journalacademicmarketingmysticismonline.net\/index.php\/JAMMO\/oai","homepageUrl":"http:\/\/www.journalacademicmarketingmysticismonline.net","software":null,"metadataFormat":"oai_dc","createdDate":"2019-06-26T08:26:01+01:00","location":{"countryCode":"","latitude":0,"longitude":0},"logo":"https:\/\/api.core.ac.uk\/data-providers\/7969\/logo","type":"JOURNAL","rorId":null,"institutionName":null,"aliases":[],"otherIdentifiers":null}