{"id":2960,"openDoarId":null,"name":"Florida State University ETD Collection","email":"","oaiPmhUrl":"http:\/\/etd.lib.fsu.edu\/ETD-db\/ETD-oai\/oai.pl","homepageUrl":"http:\/\/etd.lib.fsu.edu","software":null,"metadataFormat":"oai_dc","createdDate":"2017-08-31T15:54:01+01:00","location":{"countryCode":"us","latitude":0,"longitude":0},"logo":"https:\/\/api.core.ac.uk\/data-providers\/2960\/logo","type":"REPOSITORY","rorId":"https:\/\/ror.org\/01v4tq883","institutionName":"Florida A\u0026M University - Florida State University College of Engineering","aliases":[],"otherIdentifiers":{"GRID":{"preferred":"grid.427253.5","all":"grid.427253.5"},"Wikidata":{"all":"Q5461169"}}}