{"id":509,"openDoarId":1766,"name":"JAMSTEC Repository","email":"","oaiPmhUrl":"http:\/\/www.jamstec.go.jp\/jir\/infolib\/oai_repository\/repository","homepageUrl":"http:\/\/www.jamstec.go.jp","software":null,"metadataFormat":"oai_dc","createdDate":"2013-08-06T17:02:21+01:00","location":{"countryCode":"JP","latitude":35.2813,"longitude":139.6722},"logo":"https:\/\/api.core.ac.uk\/data-providers\/509\/logo","type":"REPOSITORY","rorId":"https:\/\/ror.org\/059qg2m13","institutionName":"Japan Agency for Marine-Earth Science and Technology","aliases":["Dokuritsu-gy\u014dsei-h\u014djin Kaiy\u014d Kenky\u016b Kaihatsu Kik\u014d","ja: \u6d77\u6d0b\u7814\u7a76\u958b\u767a\u6a5f\u69cb","JAMSTEC"],"otherIdentifiers":{"GRID":{"preferred":"grid.410588.0","all":"grid.410588.0"},"ISNI":{"all":"0000 0001 2191 0132"},"FundRef":{"all":"501100003988"},"Wikidata":{"preferred":"Q1683113","all":"Q1683113;Q27887048"}}}