{"id":375,"openDoarId":182,"name":"Open Access Repository of IISc Research Publications","email":"","oaiPmhUrl":"http:\/\/eprints.iisc.ernet.in\/cgi\/oai2","homepageUrl":"http:\/\/eprints.iisc.ernet.in","software":"eprints","metadataFormat":"oai_dc","createdDate":"2013-07-11T12:23:45+01:00","location":{"countryCode":"IN","latitude":13.0143,"longitude":77.5657},"logo":"https:\/\/api.core.ac.uk\/data-providers\/375\/logo","type":"REPOSITORY","rorId":"https:\/\/ror.org\/04dese585","institutionName":"Indian Institute of Science Bangalore","aliases":["bn: \u09ad\u09be\u09b0\u09a4\u09c0\u09af\u09bc \u09ac\u09bf\u099c\u09cd\u099e\u09be\u09a8 \u09b8\u0982\u09b8\u09cd\u09a5\u09be"," gu: \u0aad\u0abe\u0ab0\u0aa4\u0ac0\u0aaf \u0ab5\u0abf\u0a9c\u0acd\u0a9e\u0abe\u0aa8 \u0ab8\u0a82\u0ab8\u0acd\u0aa5\u0abe"," hi: \u092d\u093e\u0930\u0924\u0940\u092f \u0935\u093f\u091c\u094d\u091e\u093e\u0928 \u0938\u0902\u0938\u094d\u0925\u093e\u0928"," kn: \u0cad\u0cbe\u0cb0\u0ca4\u0cc0\u0caf \u0cb5\u0cbf\u0c9c\u0ccd\u0c9e\u0cbe\u0ca8 \u0cb8\u0c82\u0cb8\u0ccd\u0ca5\u0cc6"," ml: \u0d07\u0d28\u0d4d\u0d24\u0d4d\u0d2f\u0d7b \u0d07\u0d7b\u0d38\u0d4d\u0d31\u0d4d\u0d31\u0d3f\u0d31\u0d4d\u0d31\u0d4d\u0d2f\u0d42\u0d1f\u0d4d\u0d1f\u0d4d \u0d13\u0d2b\u0d4d \u0d38\u0d2f\u0d7b\u0d38\u0d4d"," pa: \u0a2d\u0a3e\u0a30\u0a24\u0a40 \u0a35\u0a3f\u0a17\u0a3f\u0a06\u0a28 \u0a05\u0a26\u0a3e\u0a30\u0a3e"," ta: \u0b87\u0ba8\u0bcd\u0ba4\u0bbf\u0baf \u0b85\u0bb1\u0bbf\u0bb5\u0bbf\u0baf\u0bb2\u0bcd \u0b95\u0bb4\u0b95\u0bae\u0bcd"," te: \u0c07\u0c02\u0c21\u0c3f\u0c2f\u0c28\u0c4d \u0c07\u0c28\u0c4d \u0c38\u0c4d\u0c1f\u0c3f\u0c1f\u0c4d\u0c2f\u0c42\u0c1f\u0c4d \u0c06\u0c2b\u0c4d \u0c38\u0c48\u0c28\u0c4d\u0c38\u0c4d","IISc"],"otherIdentifiers":{"GRID":{"preferred":"grid.34980.36","all":"grid.34980.36"},"ISNI":{"all":"0000 0001 0482 5067"},"FundRef":{"preferred":100007780,"all":"100007780;100009935;100008044;100007871"},"Wikidata":{"all":"Q948720"}}}