{"id":2539,"openDoarId":null,"name":"Gunadarma University Repository","email":"dashboard@core.ac.uk","oaiPmhUrl":"http:\/\/repository.gunadarma.ac.id\/cgi\/oai2","homepageUrl":"http:\/\/repository.gunadarma.ac.id","software":null,"metadataFormat":"oai_dc","createdDate":"2017-02-27T00:00:05+00:00","location":{"countryCode":"id","latitude":-6.26667,"longitude":106.8},"logo":"https:\/\/api.core.ac.uk\/data-providers\/2539\/logo","type":"REPOSITORY","rorId":"https:\/\/ror.org\/0028q1g19","institutionName":"Gunadarma University","aliases":["id: Universitas Gunadarma","UG"],"otherIdentifiers":{"GRID":{"preferred":"grid.443311.0","all":"grid.443311.0"},"ISNI":{"all":"0000 0001 0253 0425"},"FundRef":{"preferred":100018343,"all":"100018343"},"Wikidata":{"all":"Q12523328"}}}