{"id":4713,"openDoarId":null,"name":"Jurnal Pendidikan Ekonomi dan Bisnis","email":"","oaiPmhUrl":"http:\/\/journal.unj.ac.id\/unj\/index.php\/jpeb\/oai","homepageUrl":"http:\/\/journal.unj.ac.id\/unj\/index.php\/jpeb","software":"OJS","metadataFormat":"oai_dc","createdDate":"2018-07-12T14:41:49+01:00","location":{"countryCode":"","latitude":0,"longitude":0},"logo":"https:\/\/api.core.ac.uk\/data-providers\/4713\/logo","type":"JOURNAL","rorId":null,"institutionName":null,"aliases":[],"otherIdentifiers":null}