{"id":3584,"openDoarId":null,"name":"Humane Society Institute for Science and Policy","email":"","oaiPmhUrl":"http:\/\/animalstudiesrepository.org\/do\/oai","homepageUrl":"http:\/\/animalstudiesrepository.org","software":null,"metadataFormat":"oai_dc","createdDate":"2017-08-31T15:55:40+01:00","location":{"countryCode":"us","latitude":38.9072,"longitude":-77.0365},"logo":"https:\/\/api.core.ac.uk\/data-providers\/3584\/logo","type":"REPOSITORY","rorId":null,"institutionName":null,"aliases":[],"otherIdentifiers":null}