{"id":1481,"openDoarId":2498,"name":"Future University Hakodate Academic Archive","email":"awaya@fun.ac.jp","oaiPmhUrl":"http:\/\/lib-repos.fun.ac.jp\/dspace-oai\/request","homepageUrl":"http:\/\/lib-repos.fun.ac.jp","software":null,"metadataFormat":"oai_dc","createdDate":"2016-11-08T12:28:54+00:00","location":{"countryCode":"JP","latitude":41.8419,"longitude":140.7667},"logo":"https:\/\/api.core.ac.uk\/data-providers\/1481\/logo","type":"REPOSITORY","rorId":"https:\/\/ror.org\/05szw2z23","institutionName":"Future University Hakodate","aliases":["ja: \u516c\u7acb\u306f\u3053\u3060\u3066\u672a\u6765\u5927\u5b66"],"otherIdentifiers":{"GRID":{"preferred":"grid.440872.d","all":"grid.440872.d"},"ISNI":{"all":"0000 0004 0640 7610"},"Wikidata":{"all":"Q835738"}}}