{"id":405,"openDoarId":2459,"name":"edoc","email":"","oaiPmhUrl":"http:\/\/edoc.unibas.ch\/cgi\/oai2","homepageUrl":"http:\/\/edoc.unibas.ch","software":"eprints","metadataFormat":"oai_dc","createdDate":"2013-07-16T09:25:41+01:00","location":{"countryCode":"CH","latitude":47.5586,"longitude":7.5828},"logo":"https:\/\/api.core.ac.uk\/data-providers\/405\/logo","type":"REPOSITORY","rorId":"https:\/\/ror.org\/02s6k3f65","institutionName":"University of Basel","aliases":["de: Universit\u00e4t Basel"," fr: Universit\u00e9 de B\u00e2le"," it: Universit\u00e0 di Basilea"],"otherIdentifiers":{"GRID":{"preferred":"grid.6612.3","all":"grid.6612.3"},"ISNI":{"all":"0000 0004 1937 0642"},"FundRef":{"preferred":100008375,"all":"100008375;501100008595;100008550"},"Wikidata":{"all":"Q372608"}}}