{"id":839,"openDoarId":1939,"name":"Osaka City University Repository","email":"","oaiPmhUrl":"http:\/\/dlisv03.media.osaka-cu.ac.jp\/infolib\/oai_repository\/repository","homepageUrl":"http:\/\/dlisv03.media.osaka-cu.ac.jp","software":null,"metadataFormat":"oai_dc","createdDate":"2016-05-17T15:59:30+01:00","location":{"countryCode":"JP","latitude":34.5906,"longitude":135.505},"logo":"https:\/\/api.core.ac.uk\/data-providers\/839\/logo","type":"REPOSITORY","rorId":"https:\/\/ror.org\/02skfsw40","institutionName":"Osaka City University","aliases":["\u014csaka shiritsu daigaku","ja: \u5927\u962a\u5e02\u7acb\u5927\u5b66","OCU"],"otherIdentifiers":{"GRID":{"preferred":"grid.261445.0","all":"grid.261445.0"},"ISNI":{"all":"0000 0001 1009 6411"},"FundRef":{"preferred":100015062,"all":"100015062"},"Wikidata":{"all":"Q1143396"}}}