{"id":3119,"openDoarId":null,"name":"Universidad Centroamericana UCA - Nicaragua","email":"","oaiPmhUrl":"http:\/\/bjcu.uca.edu.ni:5050\/dspace-oai\/request","homepageUrl":"http:\/\/bjcu.uca.edu.ni","software":null,"metadataFormat":"oai_dc","createdDate":"2017-08-31T15:54:36+01:00","location":{"countryCode":"ni","latitude":0,"longitude":0},"logo":"https:\/\/api.core.ac.uk\/data-providers\/3119\/logo","type":"REPOSITORY","rorId":"https:\/\/ror.org\/03n0yd032","institutionName":"Central American University","aliases":["es: Universidad Centroamericana","UCA"],"otherIdentifiers":{"GRID":{"preferred":"grid.430662.5","all":"grid.430662.5"},"ISNI":{"all":"0000 0001 2109 0349"},"Wikidata":{"all":"Q1252428"}}}