{"id":831,"openDoarId":null,"name":"OPUS - Hochschulschriftenserver der Hochschule Aalen","email":"","oaiPmhUrl":"http:\/\/opus-htw-aalen.bsz-bw.de\/oai","homepageUrl":"http:\/\/opus-htw-aalen.bsz-bw.de","software":null,"metadataFormat":"oai_dc","createdDate":"2016-05-17T12:19:25+01:00","location":{"countryCode":"de","latitude":0,"longitude":0},"logo":"https:\/\/api.core.ac.uk\/data-providers\/831\/logo","type":"REPOSITORY","rorId":null,"institutionName":null,"aliases":[],"otherIdentifiers":null}