{"id":252,"openDoarId":225,"name":"Newcastle University E-Prints","email":"openaccess@ncl.ac.uk","oaiPmhUrl":"https:\/\/eprint.ncl.ac.uk\/oai\/","homepageUrl":"https:\/\/eprint.ncl.ac.uk\/","software":"eprints","metadataFormat":"oai_dc","createdDate":"2012-10-09T18:05:04+01:00","location":{"countryCode":"GB","latitude":54.9792,"longitude":-1.6147},"logo":"https:\/\/api.core.ac.uk\/data-providers\/252\/logo","type":"REPOSITORY","rorId":"https:\/\/ror.org\/01kj2bm70","institutionName":"Newcastle University","aliases":["University of Newcastle upon Tyne"],"otherIdentifiers":{"GRID":{"preferred":"grid.1006.7","all":"grid.1006.7"},"ISNI":{"all":"0000 0001 0462 7212"},"FundRef":{"all":"501100008406;501100000774"},"Wikidata":{"all":"Q837164"}}}