{"id":3597,"openDoarId":null,"name":"Rhode Island College","email":"","oaiPmhUrl":"http:\/\/digitalcommons.ric.edu\/do\/oai","homepageUrl":"http:\/\/digitalcommons.ric.edu","software":null,"metadataFormat":"oai_dc","createdDate":"2017-08-31T15:55:41+01:00","location":{"countryCode":"us","latitude":41.824,"longitude":-71.4128},"logo":"https:\/\/api.core.ac.uk\/data-providers\/3597\/logo","type":"REPOSITORY","rorId":"https:\/\/ror.org\/01k5gt570","institutionName":"Rhode Island College","aliases":["RIC"],"otherIdentifiers":{"GRID":{"preferred":"grid.262539.9","all":"grid.262539.9"},"ISNI":{"all":"0000 0004 1936 9086"},"FundRef":{"all":"100010428"},"Wikidata":{"all":"Q1613236"}}}