{"id":1805,"openDoarId":2209,"name":"National Kaohsiung Normal University Institutional Repository","email":"","oaiPmhUrl":"http:\/\/ir.lib.nknu.edu.tw\/ir\/","homepageUrl":"http:\/\/ir.lib.nknu.edu.tw","software":null,"metadataFormat":"oai_dc","createdDate":"2016-11-08T12:28:58+00:00","location":{"countryCode":"TW","latitude":22.6256,"longitude":120.32},"logo":"https:\/\/api.core.ac.uk\/data-providers\/1805\/logo","type":"REPOSITORY","rorId":"https:\/\/ror.org\/04tsc8g87","institutionName":"National Kaohsiung Normal University","aliases":["Gu\u00f3l\u00ec G\u0101oxi\u00f3ng Sh\u012bf\u00e0n D\u00e0xu\u00e9","zh: \u570b\u7acb\u9ad8\u96c4\u5e2b\u7bc4\u5927\u5b78","NKNU"],"otherIdentifiers":{"GRID":{"preferred":"grid.412076.6","all":"grid.412076.6"},"ISNI":{"all":"0000 0000 9068 9083"},"Wikidata":{"all":"Q703930"}}}