{"id":5546,"openDoarId":4123,"name":"Repository of the University of Rijeka, Faculty of Tourism and Hospitality Management, Opatija","email":"","oaiPmhUrl":"https:\/\/repository.fthm.uniri.hr\/oai","homepageUrl":null,"software":null,"metadataFormat":"oai_dc","createdDate":"2019-04-18T11:15:20+01:00","location":{"countryCode":"hr","latitude":45.3035,"longitude":14.2822},"logo":"https:\/\/api.core.ac.uk\/data-providers\/5546\/logo","type":"REPOSITORY","rorId":null,"institutionName":null,"aliases":[],"otherIdentifiers":null}