{"id":3264,"openDoarId":null,"name":"Universidad de Los Andes","email":"","oaiPmhUrl":"http:\/\/tesis.ula.ve\/pregrado\/tde_oai\/oai2.php","homepageUrl":"http:\/\/tesis.ula.ve","software":null,"metadataFormat":"oai_dc","createdDate":"2017-08-31T15:54:55+01:00","location":{"countryCode":"ve","latitude":8.6015,"longitude":-71.1487},"logo":"https:\/\/api.core.ac.uk\/data-providers\/3264\/logo","type":"REPOSITORY","rorId":"https:\/\/ror.org\/02h1b1x27","institutionName":"University of the Andes","aliases":["es: Universidad de Los Andes","ULA"],"otherIdentifiers":{"GRID":{"preferred":"grid.267525.1","all":"grid.267525.1"},"ISNI":{"all":"0000 0004 1937 0853"},"FundRef":{"preferred":501100006394,"all":"501100006394;501100006395"},"Wikidata":{"all":"Q760690"}}}