{"id":5522,"openDoarId":4052,"name":"Archivio istituzionale della Ricerca -  Universit\u00e0 degli Studi di Parma","email":"","oaiPmhUrl":"http:\/\/air.unipr.it\/oai\/request","homepageUrl":null,"software":null,"metadataFormat":"oai_dc","createdDate":"2019-04-18T11:15:15+01:00","location":{"countryCode":"it","latitude":44.8,"longitude":10.33},"logo":"https:\/\/api.core.ac.uk\/data-providers\/5522\/logo","type":"REPOSITORY","rorId":null,"institutionName":null,"aliases":[],"otherIdentifiers":null}